cache_manager.py
clapp_core.py
clean_command.py
cli_commands.py
dependency_resolver.py
doctor_command.py
info_command.py
install_command.py
installer.py
list_command.py
main.py
manifest_schema.py
manifest_validator.py
new_command.py
package_registry.py
package_runner.py
package_signing.py
platform_utils.py
post_install_hint.py
progress_utils.py
publish_command.py
remote_registry.py
smart_search.py
uninstall_command.py
update_command.py
validate_command.py
version.py
version_command.py
version_manager.py
where_command.py
clapp_pm-2.2.6.data/data/version.json
clapp_pm-2.2.6.dist-info/licenses/LICENSE
docs/developer_guide.md
packages/clapp-store/README.md
packages/clapp-store/main.py
packages/clapp-store/manifest.json
packages/clapp-store/requirements.txt
packages/clapp-store/run.py
packages/clapp-store/test_app.py
packages/cloud-notepad/README.md
packages/cloud-notepad/cloud_sync.py
packages/cloud-notepad/find_replace_dialog.py
packages/cloud-notepad/main.py
packages/cloud-notepad/manifest.json
packages/cloud-notepad/requirements.txt
packages/cloud-notepad/settings_dialog.py
packages/cloud-notepad/syntax_highlighter.py
packages/cloud-notepad/test_example.py
packages/cloud-system/README.md
packages/cloud-system/main.py
packages/cloud-system/manifest.json
packages/cloud-system/requirements.txt
packages/pycloud-os/CLOUD_APPSTORE_OZET.md
packages/pycloud-os/PYIDE_INTEGRATION_REPORT.md
packages/pycloud-os/README.md
packages/pycloud-os/TOPBAR_IKON_REHBERI.md
packages/pycloud-os/main.py
packages/pycloud-os/manifest.json
packages/pycloud-os/requirements-dev.txt
packages/pycloud-os/requirements.txt
packages/pycloud-os/setup_deps.py
packages/pycloud-os/test_cloud_appstore.py
packages/pycloud-os/test_cloud_files_launcher_integration.py
packages/pycloud-os/test_file_opening_fix.py
packages/pycloud-os/test_filepicker_gui.py
packages/pycloud-os/test_full_ecosystem_integration.py
packages/pycloud-os/test_pyos_final_integration.py
packages/pycloud-os/test_topbar_widgets.py
packages/pycloud-os/apps/app_store/README.md
clapp_pm-2.2.6.dist-info/METADATA
clapp_pm-2.2.6.dist-info/WHEEL
clapp_pm-2.2.6.dist-info/entry_points.txt
clapp_pm-2.2.6.dist-info/top_level.txt
clapp_pm-2.2.6.dist-info/RECORD
