Metadata-Version: 2.4
Name: clapp-pm
Version: 2.2.6
Summary: Lightweight cross-language app manager for Python and Lua
Home-page: https://github.com/mburakmmm/clapp
Author: Melih Burak Memiş
Author-email: Melih Burak Memiş <mburakmemiscy@gmail.com>
Maintainer-email: Melih Burak Memiş <mburakmemiscy@gmail.com>
License: MIT
Project-URL: Homepage, https://github.com/mburakmmm/clapp
Project-URL: Repository, https://github.com/mburakmmm/clapp
Project-URL: Documentation, https://github.com/mburakmmm/clapp/blob/main/README.md
Project-URL: Bug Tracker, https://github.com/mburakmmm/clapp/issues
Project-URL: Package Repository, https://github.com/mburakmmm/clapp-packages
Project-URL: Changelog, https://github.com/mburakmmm/clapp/blob/main/CHANGELOG.md
Keywords: package-manager,app-manager,python,lua,cross-language,cli,lightweight,desktop,applications
Platform: Windows
Platform: Linux
Platform: macOS
Classifier: Development Status :: 4 - Beta
Classifier: Intended Audience :: Developers
Classifier: Intended Audience :: End Users/Desktop
Classifier: License :: OSI Approved :: MIT License
Classifier: Operating System :: OS Independent
Classifier: Programming Language :: Python :: 3
Classifier: Programming Language :: Python :: 3.8
Classifier: Programming Language :: Python :: 3.9
Classifier: Programming Language :: Python :: 3.10
Classifier: Programming Language :: Python :: 3.11
Classifier: Programming Language :: Python :: 3.12
Classifier: Topic :: Software Development :: Libraries :: Python Modules
Classifier: Topic :: System :: Software Distribution
Classifier: Topic :: Utilities
Classifier: Environment :: Console
Classifier: Natural Language :: Turkish
Classifier: Natural Language :: English
Requires-Python: >=3.8
License-File: LICENSE
Requires-Dist: requests>=2.31.0
Requires-Dist: typing-extensions>=4.0.0; python_version < "3.10"
Provides-Extra: dev
Requires-Dist: pytest>=7.0.0; extra == "dev"
Requires-Dist: black>=22.0.0; extra == "dev"
Requires-Dist: flake8>=4.0.0; extra == "dev"
Requires-Dist: mypy>=0.950; extra == "dev"
Requires-Dist: pre-commit>=2.20.0; extra == "dev"
Provides-Extra: test
Requires-Dist: pytest>=7.0.0; extra == "test"
Requires-Dist: pytest-cov>=4.0.0; extra == "test"
Requires-Dist: coverage>=6.0.0; extra == "test"
Dynamic: author
Dynamic: home-page
Dynamic: license-file
Dynamic: platform
Dynamic: requires-python
